turbo_tunnel/__init__.py
turbo_tunnel/__main__.py
turbo_tunnel/auth.py
turbo_tunnel/chain.py
turbo_tunnel/conf.py
turbo_tunnel/https.py
turbo_tunnel/icmp.py
turbo_tunnel/k8s.py
turbo_tunnel/registry.py
turbo_tunnel/route.py
turbo_tunnel/server.py
turbo_tunnel/socks.py
turbo_tunnel/ssh.py
turbo_tunnel/tunnel.py
turbo_tunnel/utils.py
turbo_tunnel/websocket.py
turbo_tunnel/plugins/__init__.py
turbo_tunnel/plugins/terminal.py
turbo_tunnel-0.18.5.dist-info/LICENSE
turbo_tunnel-0.18.5.dist-info/METADATA
turbo_tunnel-0.18.5.dist-info/WHEEL
turbo_tunnel-0.18.5.dist-info/entry_points.txt
turbo_tunnel-0.18.5.dist-info/top_level.txt
turbo_tunnel-0.18.5.dist-info/RECORD
