Metadata-Version: 2.1
Name: turbo-tunnel
Version: 0.18.5
Summary: Fast tcp/https/websocket/socks4/ssh tunnel serving as unified proxy server.
Home-page: https://github.com/drunkdream/turbo-tunnel
Author: drunkdream
Author-email: drunkdream@qq.com
License: MIT
Classifier: Development Status :: 3 - Alpha
Classifier: License :: OSI Approved :: MIT License
Classifier: Programming Language :: Python
Classifier: Programming Language :: Python :: 3
Classifier: Programming Language :: Python :: 3.5
Classifier: Programming Language :: Python :: 3.6
Classifier: Programming Language :: Python :: 3.7
Classifier: Programming Language :: Python :: 3.8
Classifier: Programming Language :: Python :: 3.9
Classifier: Programming Language :: Python :: 3.10
Classifier: Programming Language :: Python :: 3.11
Classifier: Programming Language :: Python :: 3.12
Classifier: Intended Audience :: Developers
Requires-Python: >=3.5
License-File: LICENSE
Requires-Dist: async_dns
Requires-Dist: asyncssh<2.9.0,>=2.3.0; python_version >= "3.6"
Requires-Dist: cryptography<37.0.0; python_version >= "3.6"
Requires-Dist: msgpack
Requires-Dist: python-daemon==2.3.2
Requires-Dist: pyyaml
Requires-Dist: tornado==6.1
Provides-Extra: kdf
Requires-Dist: bcrypt; extra == "kdf"
